{
  "version": 2,
  "iso": "IE",
  "values": [
    {
      "key": "cost_of_living_family_150m2_in_city_center",
      "alignmentText": "EUR 4,750.00 ($5,225.00)",
      "alignmentValue": 5,
      "sameAsParent": false
    },
    {
      "key": "cost_of_living_family_150m2_on_city_edge",
      "alignmentText": "EUR 2,800.00 ($3,080.00)",
      "alignmentValue": 9
    },
    {
      "key": "cost_of_living_family_150m2_suburb",
      "alignmentText": "EUR 2,800.00 ($3,080.00)",
      "alignmentValue": 9,
      "sameAsParent": false
    },
    {
      "key": "cost_of_living_family_3_days_in_er",
      "alignmentText": "EUR 420.00 ($453.60)",
      "alignmentValue": 8,
      "sameAsParent": false
    },
    {
      "key": "cost_of_living_family_52_therapy_sessions",
      "alignmentText": "EUR 3,900.00 ($4,290.00)",
      "alignmentValue": 3,
      "sameAsParent": false
    },
    {
      "key": "cost_of_living_family_eating_out",
      "alignmentText": "EUR 120.00 ($132.00)",
      "alignmentValue": 3,
      "sameAsParent": false
    },
    {
      "key": "cost_of_living_family_health_insurance_costs",
      "alignmentText": "EUR 500.00 ($550.00)",
      "sameAsParent": false
    },
    {
      "key": "cost_of_living_family_semester_of_college_citizen",
      "alignmentText": "EUR 1,500.00 ($1,635.00)",
      "alignmentValue": 8,
      "sameAsParent": false
    },
    {
      "key": "cost_of_living_family_semester_of_college_non_resident",
      "alignmentText": "EUR 6,500.00 ($7,150.00)",
      "alignmentValue": 6
    },
    {
      "key": "cost_of_living_family_semester_of_college_perm_resident",
      "alignmentText": "EUR 1,700.00 ($1,870.00)",
      "alignmentValue": 9,
      "sameAsParent": false
    },
    {
      "key": "daemon_games_bureaucratic_compliance_effort",
      "alignmentText": "Ireland (IE): monthly payroll and quarterly VAT via CRO; a part-time accountant keeps filings manageable for a small, family-friendly game studio.",
      "alignmentValue": 7
    },
    {
      "key": "daemon_games_burn_rate",
      "alignmentText": "EUR 1,005,000.00 ($1,084,395.00)",
      "alignmentValue": 4,
      "sameAsParent": false
    },
    {
      "key": "daemon_games_corporate_tax_rate",
      "alignmentText": "12.5%",
      "alignmentValue": 10,
      "sameAsParent": false
    },
    {
      "key": "daemon_games_ease_of_entrepreneurship_visa",
      "alignmentText": "Ireland\u0027s Start-up Entrepreneur visa supports a Dublin game-studio founder; ~2-3 months for approval with ~\u20AC50k funding and startup-friendly docs.",
      "alignmentValue": 8,
      "sameAsParent": false
    },
    {
      "key": "daemon_games_employer_on_cost_rate",
      "alignmentText": "11%",
      "alignmentValue": 10
    },
    {
      "key": "daemon_games_feasible_game_grants",
      "alignmentText": "- EUR 1,200,000.00 ($1,272,000.00) \u2013 Creative Europe MEDIA \u2013 Provides narrative-driven premium-game support to Ireland-incorporated studios and eligible EU partners within 0\u20133 years with milestone-based funding.\n- EUR 900,000.00 ($955,000.00) \u2013 Screen Ireland \u2013 Video Games Fund \u2013 Supports development and production for indie studios that establish an Irish entity, with flexible terms for small teams.\n- EUR 1,000,000.00 ($1,060,000.00) \u2013 Enterprise Ireland \u2013 New Frontiers \u2013 Offers early-stage, internationally oriented startup funding and mentorship over a 2-year trajectory.\n- EUR 500,000.00 ($530,000.00) \u2013 R\u0026D Tax Credit \u2013 Ireland \u2013 Allows a 25% credit on qualifying R\u0026D expenditure, reducing development costs for an Irish-incorporated project.",
      "sameAsParent": false
    },
    {
      "key": "daemon_games_number_of_aaa_studios",
      "alignmentText": "0",
      "alignmentValue": 1
    },
    {
      "key": "daemon_games_number_of_aa_studios",
      "alignmentText": "20",
      "alignmentValue": 8
    },
    {
      "key": "daemon_games_roi_1m_units_2_years",
      "alignmentText": "EUR 10,060,386.88 ($10,935,203.13)",
      "alignmentValue": 9,
      "sameAsParent": false
    },
    {
      "key": "daemon_games_roi_400k_units_2_years",
      "alignmentText": "EUR 2,797,805.67 ($3,039,243.15)",
      "alignmentValue": 7,
      "sameAsParent": false
    },
    {
      "key": "daemon_games_roi_5m_units_2_years",
      "alignmentText": "EUR 54,448,371.25 ($59,833,375.00)",
      "alignmentValue": 9
    },
    {
      "key": "daemon_games_vibrancy_of_local_game_development_communities",
      "alignmentText": "Dublin\u0027s game dev scene has monthly meetups and a yearly jam; 250-399 online members drive collaborations in Dublin\u2014great for an entrepreneur family.",
      "alignmentValue": 7
    },
    {
      "key": "daemon_games_yearly_office_space_cost",
      "alignmentText": "EUR 40,000.00 ($42,800.00)",
      "alignmentValue": 8,
      "sameAsParent": false
    },
    {
      "key": "integration_adult_language_expectations",
      "alignmentText": "In Ireland (IE), English is dominant. Most government, healthcare, and banking tasks are in English; Gaelic use is limited.",
      "alignmentValue": 10
    },
    {
      "key": "integration_childhood_language_expectations",
      "alignmentText": "IE: public schools are English-dominated; bilingual options exist mainly in Gaelscoileanna; Irish immersion not common from kindergarten.",
      "alignmentValue": 3,
      "sameAsParent": false
    },
    {
      "key": "integration_housing_accessibility",
      "alignmentText": "Ireland rental market: 4-6 weeks to lease; deposits up to 2.5 months; guarantor commonly requested for newcomers.",
      "alignmentValue": 7
    },
    {
      "key": "integration_immigration_status_rights",
      "alignmentText": "Ireland offers two main immigration tracks: citizenship and long-term residency. Citizenship can be acquired by birth/descent (if a parent is an Irish citizen or under certain conditions) or by naturalisation after meeting residence requirements (typically about 5 years of lawful residence in the last 9 years, including 12 months continuous residence). Rights conferred: Irish passport; live/work anywhere in Ireland and the EU; access to public services and social benefits; eligibility to vote in national elections. Long-term residency (EU long-term resident status or Stamp 4) is usually available after around 5 years of lawful residence and satisfactory character checks; rights include the ability to reside and work in Ireland without a separate work permit, access to healthcare and welfare on par with nationals, and a pathway to permanent residency and eventual citizenship. Stamp 4 can apply to qualifying family members (e.g., spouses of Irish citizens); rights include unrestricted work and study rights and access to services, with potential upgrade to long-term residency later. Action steps: assess eligibility for each path, gather documents (passports, birth/marriage certificates, proof of residence and income), consult INIS or an immigration adviser, and plan timelines toward naturalisation or permanent residence."
    },
    {
      "key": "integration_welcoming_of_skilled_immigrants",
      "alignmentText": "Ireland (IE) warmly welcomes skilled immigrants; strong tech scene and English language ease help founders and families.",
      "alignmentValue": 9
    },
    {
      "key": "kids_bullying_and_racism",
      "alignmentText": "Ireland schools enforce anti-bullying policies; US expat children integrate well with a low bullying risk (about 1-2 per 1,000).",
      "alignmentValue": 9,
      "sameAsParent": false
    },
    {
      "key": "kids_education_quality",
      "alignmentText": "Ireland offers solid primary/secondary education with universal access and bilingual options; strong public schools support kids.",
      "alignmentValue": 7,
      "sameAsParent": false
    },
    {
      "key": "kids_food_quality",
      "alignmentText": "Ireland\u0027s school meals are improving; HEI ~70\u201374 with ultra-processed calories under 15%.",
      "alignmentValue": 6,
      "sameAsParent": false
    },
    {
      "key": "kids_language_expectations_in_schools",
      "alignmentText": "Public schools in Ireland are English-medium; Irish is compulsory. Expect 12-13 hours of English weekly with some bilingual support.",
      "alignmentValue": 7
    },
    {
      "key": "kids_language_integration_services",
      "alignmentText": "Ireland offers robust ESOL access and translations at essential services; newcomer kids in IE benefit from strong language integration.",
      "alignmentValue": 9,
      "sameAsParent": false
    },
    {
      "key": "leisure_common_date_night_opportunities",
      "alignmentText": "Ireland: focus on early-evening, family-friendly date options in Dublin, Cork, and Galway\u2014kid-friendly restaurants with early seating, well-lit parks for post-dinner strolls, and short cultural activities; arrange trusted babysitting in advance to enable a true date night; prioritize venues with good transit access and affordable parking.",
      "sameAsParent": false
    },
    {
      "key": "leisure_common_family_activity_opportunities",
      "alignmentText": "Plan a rotating calendar of Ireland-based family activities that mix outdoor parks and beaches with kid-friendly cultural venues within a 1-2 hour drive. Action steps: map regular visits to parks and coast (Phoenix Park, Howth, Bray), plan day trips to nature areas (Wicklow Mountains, Glendalough) and family venues (Imaginosity Dublin; Fota Wildlife Park near Cork; King John\u0027s Castle and Hunt Museum in Limerick). Include libraries with children\u0027s programs and indoor play centres for rainy days; prioritize affordable options and accessibility for a 5-year-old and a 1-year-old, and plan around daylight and weather."
    },
    {
      "key": "leisure_common_friend_night_opportunities",
      "alignmentText": "Ireland (IE): Seek family-friendly evening options such as library/storytime and community-center activities after 6 pm, twilight park meetups and playgroups, kid-friendly screenings or workshops at museums or cinemas, and family volunteering or community events; consider joining local parent groups or Meetups to build social connections in walkable, safe neighborhoods with reliable childcare if needed.",
      "sameAsParent": false
    },
    {
      "key": "leisure_parent_friendly_3rd_places",
      "alignmentText": "Ireland offers parent-friendly 3rd places. Urban libraries and community centers provide after-6pm supervised options.",
      "alignmentValue": 7
    },
    {
      "key": "leisure_peoples_centric_cities",
      "alignmentText": "In Ireland\u0027s urban centers (Dublin, Cork), walk/bike/transit fit; about 50\u201359% of trips can be car-free for a family.",
      "alignmentValue": 7
    },
    {
      "key": "leisure_quality_food_access",
      "alignmentText": "IE urban areas offer 2-3 farmers markets per 100k with fresh options; fast-food density is moderate, supporting family meals in Ireland.",
      "alignmentValue": 6,
      "sameAsParent": false
    },
    {
      "key": "life_bureaucratic_compliance_effort",
      "alignmentText": "Ireland\u0027s mygov.ie/INIS portals keep visa and tax tasks online; ongoing compliance about 1-2 hours/mo, with a one-time initial set-up.",
      "alignmentValue": 8,
      "sameAsParent": false
    },
    {
      "key": "life_daycare_accessibility",
      "alignmentText": "Placement for infants in Ireland commonly runs 4-6 months; urban areas vary - consider private centres and government schemes.",
      "alignmentValue": 6,
      "sameAsParent": false
    },
    {
      "key": "life_daycare_affordability_citizen",
      "alignmentText": "EUR 1,000.00 ($1,100.00)",
      "alignmentValue": 1
    },
    {
      "key": "life_daycare_affordability_non_resident",
      "alignmentText": "EUR 1,150.00 ($1,265.00)",
      "alignmentValue": 4,
      "sameAsParent": false
    },
    {
      "key": "life_daycare_affordability_perm_resident",
      "alignmentText": "EUR 1,000.00 ($1,100.00)",
      "alignmentValue": 1
    },
    {
      "key": "life_healthcare_accessibility",
      "alignmentText": "Ireland (IE) offers universal healthcare; for a family in IE, GP visits are 5-7 days and specialists 11-14 days.",
      "alignmentValue": 7
    },
    {
      "key": "life_healthcare_affordability_citizen",
      "alignmentText": "EUR 450.00 ($486.00)",
      "alignmentValue": 10
    },
    {
      "key": "life_healthcare_affordability_non_resident",
      "alignmentText": "EUR 550.00 ($590.00)",
      "alignmentValue": 10,
      "sameAsParent": false
    },
    {
      "key": "life_healthcare_affordability_perm_resident",
      "alignmentText": "EUR 850.00 ($935.00)",
      "alignmentValue": 9,
      "sameAsParent": false
    },
    {
      "key": "life_healthcare_tied_to_employment",
      "alignmentText": "Ireland (IE) has universal public care, but many rely on employer private plans; leaving a job could risk 11-20% losing coverage.",
      "alignmentValue": 8
    },
    {
      "key": "life_hours_worked_per_year",
      "alignmentText": "1848",
      "alignmentValue": 7
    },
    {
      "key": "life_public_transportation",
      "alignmentText": "Dublin, Ireland: transit is strong; many inner suburbs sit within 500m of 10-minute buses/trams for ~18 hours daily. Good for families.",
      "alignmentValue": 9
    },
    {
      "key": "opportunity_college_accessibility",
      "alignmentText": "Ireland: non-EU tuition is not free; expect about 19-21% of income with 40-44% admission for many programs. Seek scholarships/grants.",
      "alignmentValue": 3
    },
    {
      "key": "opportunity_college_quality",
      "alignmentText": "Ireland\u0027s universities (e.g., Dublin) sit 101\u2013300 globally with English programs, aligning with your high-quality education goals and English ubiquity.",
      "alignmentValue": 6
    },
    {
      "key": "opportunity_continuing_education_accessibility",
      "alignmentText": "Ireland (IE) offers strong continuing education with many accredited programs. Subsidized Springboard\u002B options support Trey\u0027s upskilling.",
      "alignmentValue": 9
    },
    {
      "key": "opportunity_demand_for_dotnet_architect",
      "alignmentText": "Ireland\u0027s senior .NET architect demand remains strong. Dublin\u0027s tech scene supports remote/hybrid roles and English-friendly pathways.",
      "alignmentValue": 9
    },
    {
      "key": "opportunity_demand_for_ruby_on_rails",
      "alignmentText": "Ireland (Dublin region) Rails demand ~15-19 postings/m; steady for 6 years\u0027 experience; not saturated.",
      "alignmentValue": 6,
      "sameAsParent": false
    },
    {
      "key": "opportunity_salary_for_dotnet_architect",
      "alignmentText": "EUR 140,000.00 ($152,600.00)"
    },
    {
      "key": "opportunity_salary_for_ruby_on_rails",
      "alignmentText": "EUR 75,000.00 ($81,750.00)"
    },
    {
      "key": "outdoors_beach_life",
      "alignmentText": "Target coastal Ireland towns with blue-flag beaches within a reasonable radius of Dublin and regional centers (e.g., Howth, Portmarnock, Salthill, Inchydoney). Prioritize family-friendly neighborhoods near the beach with reliable broadband, parks, indoor options for rainy days, strong schools/childcare, affordable housing, and access to public services; ensure mild climate, low crime, and a supportive remote-work/startup ecosystem to support Trey and Sarah."
    },
    {
      "key": "outdoors_fall_temperature_range",
      "alignmentText": "Fall in Dublin, Ireland: highs 55\u201372\u00B0F, lows 45\u201355\u00B0F; mild, with gentle cool-down.",
      "alignmentValue": 9,
      "sameAsParent": false
    },
    {
      "key": "outdoors_mild_weather",
      "alignmentText": "Ireland\u0027s temperate maritime climate offers many comfortable days per year; humidity can be damp, especially near the coast.",
      "alignmentValue": 8,
      "sameAsParent": false
    },
    {
      "key": "outdoors_natural_beauty",
      "alignmentText": "In Ireland\u0027s Dublin region, Wicklow Mountains, Glendalough, and Howth Cliffs are within an hour; ~40-49% protected lands nearby.",
      "alignmentValue": 9,
      "sameAsParent": false
    },
    {
      "key": "outdoors_nature_access",
      "alignmentText": "Ireland provides solid nature access for families: many parks \u003E10 acres within 5 km and regional trails reachable by transit in under 30 minutes.",
      "alignmentValue": 7,
      "sameAsParent": false
    },
    {
      "key": "outdoors_spring_temperature_range",
      "alignmentText": "Spring in Ireland (IE) typically ranges 48\u201365\u00B0F by day and 36\u201346\u00B0F at night. Expect frequent rain; mild, changeable days suit a family-friendly plan.",
      "alignmentValue": 6,
      "sameAsParent": false
    },
    {
      "key": "outdoors_summer_temperature_range",
      "alignmentText": "Ireland (IE) summers typically reach 70-82\u00B0F with nights 60-70\u00B0F and generally low humidity; heatwaves are rare.",
      "alignmentValue": 10,
      "sameAsParent": false
    },
    {
      "key": "outdoors_winter_temperature_range",
      "alignmentText": "Winter in Ireland (IE) typically highs 45\u00B0F\u201360\u00B0F and lows 32\u00B0F\u201345\u00B0F with little snow. This aligns with your mild-weather, low-risk climate preference.",
      "alignmentValue": 10,
      "sameAsParent": false
    },
    {
      "key": "stability_climate_stability",
      "alignmentText": "Ireland, IE offers a mild, temperate climate with few severe-weather days. It supports a low-stress, family-friendly lifestyle.",
      "alignmentValue": 9,
      "sameAsParent": false
    },
    {
      "key": "stability_economic_stability",
      "alignmentText": "Ireland shows stability with only two negative real GDP years (2009, 2020); solid for family plans in IE.",
      "alignmentValue": 9
    },
    {
      "key": "stability_migration_stability",
      "alignmentText": "Stable immigration climate in Ireland (IE), including Dublin; English ubiquity; startup-friendly visas with modest, predictable policy updates.",
      "alignmentValue": 9
    },
    {
      "key": "stability_political_stability",
      "alignmentText": "Ireland sits in the top tier of the V-Dem Liberal Democracy Index with strong, predictable governance; ideal for families and startups in IE.",
      "alignmentValue": 10
    },
    {
      "key": "stability_social_and_quality_of_life_stability",
      "alignmentText": "Ireland has very low violent crime (well under 200/100k) and universal healthcare. This supports a stable, family-friendly life for Trey, Sarah and their kids.",
      "alignmentValue": 10
    },
    {
      "key": "integration_immigration_timeline_entrepreneur",
      "alignmentText": "Ireland Start-up Entrepreneur visa end-to-end often 21-28 weeks; plan for 5-7 months with approvals in IE.",
      "alignmentValue": 3
    },
    {
      "key": "integration_immigration_timeline_without_recognized_sponsor",
      "alignmentText": "Ireland\u0027s non-recognized-sponsor path for a US family is slow; expect 28\u002B weeks end-to-end. Consider startup programs or a recognized sponsor route.",
      "alignmentValue": 2
    },
    {
      "key": "integration_immigration_timeline_with_recognized_sponsor",
      "alignmentText": "Ireland\u0027s recognized-sponsor visa path is typically about 11-12 weeks end-to-end; plan startup/permit timelines in Ireland (Dublin).",
      "alignmentValue": 6
    },
    {
      "key": "stability_anti_immigrant_political_rhetoric",
      "alignmentText": "In Ireland, anti-immigrant rhetoric is not dominant; expect a stable, family-friendly climate with inclusive immigration and housing policies.",
      "alignmentValue": 7,
      "sameAsParent": false
    },
    {
      "key": "stability_autocratization_trend",
      "alignmentText": "Ireland (IE) shows stable democracy with near-zero autocratization over 10-20 years, supporting civil liberties and family-friendly living.",
      "alignmentValue": 10
    },
    {
      "key": "stability_dominant_political_narratives",
      "alignmentText": "Dominant narratives in Ireland center on expanding affordable housing and reducing cost of living, reforming healthcare and reducing wait times, managing energy prices while pursuing climate action, maintaining tax and economic stability, investing in rural infrastructure, and navigating EU/NI relations post-Brexit; immigration and social inclusion remain key policy axes.",
      "sameAsParent": false
    },
    {
      "key": "stability_media_freedom",
      "alignmentText": "Ireland\u0027s media freedom remains strong; independent outlets protect pluralistic reporting across Dublin and the country.",
      "alignmentValue": 10,
      "sameAsParent": false
    },
    {
      "key": "stability_wealth_inequality_level",
      "alignmentText": "Ireland\u0027s Gini ~31 indicates moderate inequality; strong services and English ubiquity support a family-friendly life in Ireland.",
      "alignmentValue": 8,
      "sameAsParent": false
    }
  ]
}