{
  "version": 2,
  "iso": "RU",
  "values": [
    {
      "key": "Environment",
      "alignmentText": "Wild taiga and lake districts are beautiful, yet pollution around industrial hubs limits easy weekend escapes.",
      "alignmentValue": 4
    },
    {
      "key": "Global Warming Risk",
      "alignmentText": "Permafrost melt, Siberian wildfires, and volatile harvests signal rising climate risk.",
      "alignmentValue": 3
    },
    {
      "key": "Seasonal Weather",
      "alignmentText": "Winters plunge well below freezing and summers swing hot, far from the family’s mild-climate goal.",
      "alignmentValue": 2
    },
    {
      "key": "Air Quality",
      "alignmentText": "Major cities regularly exceed PM limits due to coal heat and traffic, though coastal and northern towns fare better.",
      "alignmentValue": 4
    },
    {
      "key": "Natural Disasters",
      "alignmentText": "Flooding, wildfires, and thawing permafrost threaten infrastructure in multiple regions.",
      "alignmentValue": 4
    },
    {
      "key": "Spring Temperature Range (C/F)",
      "alignmentText": "Around 0–10°C (32–50°F) with lingering snow and muddy thaw.",
      "alignmentValue": 3
    },
    {
      "key": "Summer Temperature Range (C/F)",
      "alignmentText": "Moscow and Saint Petersburg average 20–26°C (68–79°F) but heatwaves now top 32°C (90°F).",
      "alignmentValue": 4
    },
    {
      "key": "Fall Temperature Range (C/F)",
      "alignmentText": "Cool 5–10°C (41–50°F) with early frosts and shortening daylight.",
      "alignmentValue": 3
    },
    {
      "key": "Winter Temperature Range (C/F)",
      "alignmentText": "Extended stretches below -10°C (14°F) demand heavy gear and limit outdoor family time.",
      "alignmentValue": 2
    },
    {
      "key": "Beach Life",
      "alignmentText": "Beaches mainly on the distant Black Sea; limited access from central cities.",
      "alignmentValue": 2
    },
    {
      "key": "Seasonal Beach Water Temp",
      "alignmentText": "Black Sea peaks near 20–24°C (68–75°F) in summer, but season is short.",
      "alignmentValue": 4
    },
    {
      "key": "Natural Beauty",
      "alignmentText": "Dramatic mountains, lakes, and tundra offer striking scenery for adventurous families.",
      "alignmentValue": 8
    },
    {
      "key": "Minimum Wage",
      "alignmentText": "Regional minimums often sit under 20,000 RUB (~$220), insufficient for a four-person household.",
      "alignmentValue": 2
    },
    {
      "key": "Typical Software Salaries",
      "alignmentText": "Senior engineers may earn 2–3 million RUB annually, but currency controls complicate international pay.",
      "alignmentValue": 4
    },
    {
      "key": ".NET Work Prospects",
      "alignmentText": "Banks and state enterprises keep .NET roles available, yet most require in-country presence.",
      "alignmentValue": 4
    },
    {
      "key": "Ruby Work Prospects",
      "alignmentText": "Ruby teams exist in e-commerce, but many companies relocated talent after 2022.",
      "alignmentValue": 3
    },
    {
      "key": "Employer Visa Sponsorship",
      "alignmentText": "US citizens face severe scrutiny; few employers will undertake sponsorship amid geopolitical tension.",
      "alignmentValue": 1
    },
    {
      "key": "Economic Health",
      "alignmentText": "Sanctions and wartime spending warp the economy, limiting entrepreneurial stability.",
      "alignmentValue": 3
    },
    {
      "key": "Remote-Friendly Culture",
      "alignmentText": "Broadband is fast in cities, but VPNs are required for many Western services and censorship is tightening.",
      "alignmentValue": 4
    },
    {
      "key": "Work-Life Balance",
      "alignmentText": "Tech teams often expect late hours during releases, and vacation can be curtailed by staffing pressures.",
      "alignmentValue": 4
    },
    {
      "key": "Work Week Hours",
      "alignmentText": "Standard 40‑hour week with overtime common in private sector.",
      "alignmentValue": 5
    },
    {
      "key": "Vacation Days (Minimum)",
      "alignmentText": "Employees receive at least 28 days plus public holidays, supporting extended travel.",
      "alignmentValue": 7
    },
    {
      "key": "Vacation Days (Typical)",
      "alignmentText": "Many staff take the legal minimum, and managers sometimes discourage long absences.",
      "alignmentValue": 6
    },
    {
      "key": "Pace of Life",
      "alignmentText": "Major metros move fast with long commutes; only smaller regional cities offer slower rhythms.",
      "alignmentValue": 4
    },
    {
      "key": "Typical Workday Schedule (Family of Four)",
      "alignmentText": "Schools run 8:30–14:30 and parents often extend days with extracurriculars to cover childcare gaps.",
      "alignmentValue": 4
    },
    {
      "key": "Typical Weekend Schedule (Family of Four)",
      "alignmentText": "Families split time between city parks and dachas, though political rallies can disrupt public events.",
      "alignmentValue": 5
    },
    {
      "key": "Family Life",
      "alignmentText": "Strong extended-family ties yet conservative expectations around roles.",
      "alignmentValue": 4
    },
    {
      "key": "Polyamory",
      "alignmentText": "Non‑monogamous relationships lack legal recognition and face social disapproval.",
      "alignmentValue": 1
    },
    {
      "key": "Parenting Expectations",
      "alignmentText": "Traditional gendered roles prevail, with heavy emphasis on discipline.",
      "alignmentValue": 3
    },
    {
      "key": "Child-Friendliness of Cities",
      "alignmentText": "Playgrounds exist but infrastructure is aging and car-heavy.",
      "alignmentValue": 4
    },
    {
      "key": "Schooling Options",
      "alignmentText": "Public schools vary widely in quality; expat or private schools mainly in major cities.",
      "alignmentValue": 3
    },
    {
      "key": "Pre-K / Early Childcare Landscape",
      "alignmentText": "State kindergartens have long waitlists, pushing families toward costly private options.",
      "alignmentValue": 3
    },
    {
      "key": "Childcare Support (Citizens)",
      "alignmentText": "Some subsidies and maternity capital, but bureaucracy is high.",
      "alignmentValue": 4
    },
    {
      "key": "Childcare Support (Visa Holders)",
      "alignmentText": "Foreign families rarely qualify for benefits and face registration hurdles.",
      "alignmentValue": 2
    },
    {
      "key": "K-12 Education Access (Citizens)",
      "alignmentText": "Guaranteed enrollment though quality differs regionally.",
      "alignmentValue": 5
    },
    {
      "key": "K-12 Education Access (Visa Holders)",
      "alignmentText": "Possible with proper permits but documentation can be burdensome.",
      "alignmentValue": 4
    },
    {
      "key": "Private Education",
      "alignmentText": "International schools exist in major hubs but are expensive and few.",
      "alignmentValue": 5
    },
    {
      "key": "Family Policy (Citizens)",
      "alignmentText": "Pronatalist incentives like tax breaks exist yet favor traditional households.",
      "alignmentValue": 3
    },
    {
      "key": "Family Policy (Visa Holders)",
      "alignmentText": "Most benefits exclude non-citizens, leaving expat families with minimal support.",
      "alignmentValue": 2
    },
    {
      "key": "Higher Education Access (Citizens)",
      "alignmentText": "Numerous universities with strong STEM but variable pedagogy.",
      "alignmentValue": 5
    },
    {
      "key": "Higher Education Access (Visa Holders)",
      "alignmentText": "Foreign students may enroll but visas and language exams add friction.",
      "alignmentValue": 3
    },
    {
      "key": "Gender Roles",
      "alignmentText": "Society stresses conventional male breadwinner and female caregiver roles.",
      "alignmentValue": 2
    },
    {
      "key": "Gender Fluidity",
      "alignmentText": "Trans and nonbinary identities face legal and social suppression.",
      "alignmentValue": 1
    },
    {
      "key": "Gender Rights",
      "alignmentText": "Domestic violence laws are weak and pay gaps persist.",
      "alignmentValue": 3
    },
    {
      "key": "Femininity Norms",
      "alignmentText": "Expectations around appearance and motherhood remain strong.",
      "alignmentValue": 2
    },
    {
      "key": "Masculinity Norms",
      "alignmentText": "Cultural emphasis on toughness and military service influences male roles.",
      "alignmentValue": 2
    },
    {
      "key": "What Is Intriguing",
      "alignmentText": "Rich literary tradition and unique art scenes may appeal to culture-seeking families.",
      "alignmentValue": 6
    },
    {
      "key": "Language & English Ubiquity",
      "alignmentText": "Outside international firms, daily life requires Russian for paperwork and social integration.",
      "alignmentValue": 3
    },
    {
      "key": "Progressivism",
      "alignmentText": "State ideology leans nationalist and socially conservative, clashing with the family’s progressive values.",
      "alignmentValue": 1
    },
    {
      "key": "Marxism (Societal Attitudes)",
      "alignmentText": "Post-Soviet nostalgia persists, but Marxism has little policy impact.",
      "alignmentValue": 4
    },
    {
      "key": "Atheism",
      "alignmentText": "Secularism coexists with a resurgence of Orthodox Christianity.",
      "alignmentValue": 5
    },
    {
      "key": "Sex (Attitudes)",
      "alignmentText": "Public discourse is reserved and sex education sparse.",
      "alignmentValue": 2
    },
    {
      "key": "LGBTQ+ Attitudes",
      "alignmentText": "Broad anti-\"propaganda\" laws criminalize queer visibility, making it unsafe for polyamory-positive families.",
      "alignmentValue": 1
    },
    {
      "key": "Community Vibes",
      "alignmentText": "Neighborhood networks are close-knit but can be wary of outspoken foreigners.",
      "alignmentValue": 3
    },
    {
      "key": "View of self",
      "alignmentText": "Strong national pride and sense of exceptionalism.",
      "alignmentValue": 4
    },
    {
      "key": "View of Neighboring Countries",
      "alignmentText": "Relations range from alliance to open conflict, reflecting geopolitical tensions.",
      "alignmentValue": 2
    },
    {
      "key": "View of Them by Neighboring Countries",
      "alignmentText": "Many neighbors harbor mistrust due to recent aggression.",
      "alignmentValue": 2
    },
    {
      "key": "Nightlife Culture",
      "alignmentText": "Vibrant clubs and late-night cafes thrive in big cities despite social conservatism.",
      "alignmentValue": 6
    },
    {
      "key": "Fashion Trends (Male)",
      "alignmentText": "Styles mix sporty casual with formal suits in urban centers.",
      "alignmentValue": 4
    },
    {
      "key": "Fashion Trends (Female)",
      "alignmentText": "Urban women often embrace European chic and high heels.",
      "alignmentValue": 5
    },
    {
      "key": "Common Hobbies",
      "alignmentText": "Ice skating, soccer, and dacha gardening are widespread pastimes.",
      "alignmentValue": 5
    },
    {
      "key": "Boardgaming & Tabletop",
      "alignmentText": "Niche communities exist but access to new imports is limited by sanctions.",
      "alignmentValue": 4
    },
    {
      "key": "Nightlife & Music",
      "alignmentText": "Strong electronic and classical scenes offer varied evening options.",
      "alignmentValue": 6
    },
    {
      "key": "Meetups & Communities",
      "alignmentText": "Tech meetups occur in major cities but many organizers have emigrated.",
      "alignmentValue": 4
    },
    {
      "key": "Nature Access",
      "alignmentText": "Forests and parks abound, yet distances and transport can be challenging.",
      "alignmentValue": 5
    },
    {
      "key": "Political System",
      "alignmentText": "Power concentrates in the presidency with managed elections and limited opposition.",
      "alignmentValue": 1
    },
    {
      "key": "Religion in Politics",
      "alignmentText": "Orthodox Church wields soft power in social policy debates.",
      "alignmentValue": 3
    },
    {
      "key": "Workers' Rights",
      "alignmentText": "Labor laws exist but enforcement is inconsistent, especially for migrants.",
      "alignmentValue": 3
    },
    {
      "key": "State Ideology",
      "alignmentText": "Nationalist rhetoric emphasizes sovereignty over liberal values.",
      "alignmentValue": 2
    },
    {
      "key": "Authoritarian Backsliding Risk",
      "alignmentText": "Ongoing crackdowns on media and NGOs show active democratic erosion.",
      "alignmentValue": 1
    },
    {
      "key": "State of Capitalism",
      "alignmentText": "Oligarchic capitalism concentrates wealth and limits entrepreneurship.",
      "alignmentValue": 2
    },
    {
      "key": "Stability",
      "alignmentText": "Institutions appear stable but mobilization and war-related sanctions create daily uncertainty.",
      "alignmentValue": 2
    },
    {
      "key": "Propaganda Prevalence",
      "alignmentText": "State media dominates news and shapes public opinion.",
      "alignmentValue": 1
    },
    {
      "key": "Propaganda Messaging",
      "alignmentText": "Narratives stress Western hostility and patriotic duty.",
      "alignmentValue": 1
    },
    {
      "key": "Social Policies",
      "alignmentText": "Benefits prioritize traditional families and military service over inclusive support.",
      "alignmentValue": 3
    },
    {
      "key": "Trust in Government",
      "alignmentText": "Polling shows reported trust, yet it’s shaped by state media and limited alternatives.",
      "alignmentValue": 3
    },
    {
      "key": "Perceived Corruption",
      "alignmentText": "Russia ranks near the bottom globally, with corruption embedded in many transactions.",
      "alignmentValue": 2
    },
    {
      "key": "Type of Corruption",
      "alignmentText": "Bribes and patronage networks influence everything from courts to utilities.",
      "alignmentValue": 2
    },
    {
      "key": "Housing Situation",
      "alignmentText": "Renovated flats in safe districts command high prices, while Soviet-era blocks need costly upgrades.",
      "alignmentValue": 3
    },
    {
      "key": "Safety & Crime",
      "alignmentText": "Street crime is moderate, but arbitrary policing and political risk add stress.",
      "alignmentValue": 3
    },
    {
      "key": "Healthcare (Citizens)",
      "alignmentText": "Universal coverage struggles with staffing shortages and outdated equipment outside flagship hospitals.",
      "alignmentValue": 3
    },
    {
      "key": "Healthcare (Visa Holders)",
      "alignmentText": "Expats rely on private clinics for quality care and often plan for evacuation insurance.",
      "alignmentValue": 2
    },
    {
      "key": "Child Care Support",
      "alignmentText": "Public kindergartens exist but have waitlists, especially in major cities.",
      "alignmentValue": 3
    },
    {
      "key": "Family Policy (Common Family)",
      "alignmentText": "Government incentives encourage larger families yet overlook diverse structures.",
      "alignmentValue": 3
    },
    {
      "key": "Education",
      "alignmentText": "STEM instruction is strong, yet civic curriculum emphasizes state narratives that conflict with progressive values.",
      "alignmentValue": 4
    },
    {
      "key": "Public Transportation",
      "alignmentText": "Moscow and Saint Petersburg boast efficient metros, though regional coverage is patchier.",
      "alignmentValue": 6
    },
    {
      "key": "Economic System",
      "alignmentText": "State-owned giants and sanctions limit competition and access to Western markets.",
      "alignmentValue": 3
    },
    {
      "key": "How Taxes Are Handled",
      "alignmentText": "Flat income tax keeps filing simple, but currency controls and reporting rules complicate expat finances.",
      "alignmentValue": 4
    },
    {
      "key": "Expected Tax Rate (Our Family)",
      "alignmentText": "Residents pay 13–15% income tax, yet double-tax treaties and sanctions make compliance tricky.",
      "alignmentValue": 4
    },
    {
      "key": "Banking & Payments",
      "alignmentText": "Domestic cards and QR payments work, but international transfers and cards remain heavily restricted.",
      "alignmentValue": 3
    },
    {
      "key": "Cost of Living (Optional)",
      "alignmentText": "Groceries and transit stay affordable, while imported goods and tuition have spiked.",
      "alignmentValue": 5
    },
    {
      "key": "Retirement (Citizens)",
      "alignmentText": "Pension system faces funding gaps and rising retirement ages.",
      "alignmentValue": 3
    },
    {
      "key": "Retirement (Visa Holders)",
      "alignmentText": "Foreign residents generally ineligible for state pensions.",
      "alignmentValue": 2
    },
    {
      "key": "Visa Paths",
      "alignmentText": "Investor and work visas exist on paper, yet approvals for US applicants are exceedingly rare.",
      "alignmentValue": 1
    },
    {
      "key": "Welcoming of US Migrants",
      "alignmentText": "US citizens face heightened scrutiny amid strained relations.",
      "alignmentValue": 1
    },
    {
      "key": "Residency Types & Durations",
      "alignmentText": "Temporary residence requires employer or family sponsorship and strict annual reporting.",
      "alignmentValue": 2
    },
    {
      "key": "Path to Citizenship",
      "alignmentText": "Naturalization generally demands five years, Russian fluency, and loyalty oaths, with security vetting.",
      "alignmentValue": 2
    },
    {
      "key": "Family Members",
      "alignmentText": "Dependents can join but face registration, schooling, and healthcare hurdles.",
      "alignmentValue": 2
    },
    {
      "key": "Timelines & Costs",
      "alignmentText": "Processing can take months with fees for translations and registrations.",
      "alignmentValue": 2
    },
    {
      "key": "Compliance & Risks",
      "alignmentText": "Registration lapses, political speech, or visa technicalities can trigger fines or deportation.",
      "alignmentValue": 1
    },
    {
      "key": "Dual Citizenship Allowed",
      "alignmentText": "Permitted but citizens must notify authorities and may face obligations.",
      "alignmentValue": 5
    },
    {
      "key": "General Considerations for Visa Holders",
      "alignmentText": "Expect travel restrictions, data monitoring, and difficulties accessing Western platforms for work.",
      "alignmentValue": 2
    },
    {
      "key": "Game Dev Work Prospects",
      "alignmentText": "Studios operate, but sanctions limit publishing and many peers have relocated.",
      "alignmentValue": 2
    },
    {
      "key": "Notable Game Studios",
      "alignmentText": "Teams like Gaijin and Saber keep Russian branches, though leadership often sits abroad.",
      "alignmentValue": 3
    },
    {
      "key": "Notable Game Development Communities",
      "alignmentText": "Meetups persist but are smaller due to emigration and censorship concerns.",
      "alignmentValue": 2
    },
    {
      "key": "Opportunities for Video Game Startup",
      "alignmentText": "Access to capital and global distribution is severely limited under sanctions.",
      "alignmentValue": 1
    },
    {
      "key": "Modernity & Infrastructure",
      "alignmentText": "Urban infrastructure remains modern, yet import bans create maintenance challenges and rural gaps.",
      "alignmentValue": 4
    },
    {
      "key": "Seasonal Extremes & Variability",
      "alignmentText": "Dangerous extremes are routine, forcing us to track emergency alerts and modify plans multiple times a quarter. Seasonal Weather at 2/10 and Natural Disasters at 4/10 steer the family toward a challenging outlook for seasonal extremes & variability.",
      "alignmentValue": 3
    },
    {
      "key": "Seasonal Sunlight Hours",
      "alignmentText": "Extreme light swings dominate lifestyle planning with regular sleep disruption and mood crashes even with preparation. Seasonal Weather at 2/10 and Environment at 4/10 steer the family toward a challenging outlook for seasonal sunlight hours.",
      "alignmentValue": 3
    },
    {
      "key": "Pleasant Weather Windows",
      "alignmentText": "Comfortable days are infrequent; we constantly monitor forecasts to grab the odd mild afternoon. Seasonal Weather at 2/10 and Environment at 4/10 steer the family toward a challenging outlook for pleasant weather windows.",
      "alignmentValue": 3
    },
    {
      "key": "Quality of Life – Lower-Income Tier",
      "alignmentText": "Survival dominates—frequent trade-offs between rent, food, and healthcare with minimal institutional help. Minimum Wage at 2/10, Housing Situation at 3/10, and Childcare Support (Citizens) at 4/10 steer the family toward a challenging outlook for quality of life – lower-income tier.",
      "alignmentValue": 3
    },
    {
      "key": "Quality of Life – Middle-Income Tier",
      "alignmentText": "Lifestyle feels brittle; one unexpected expense forces significant cutbacks or debt. Typical Software Salaries at 4/10, Housing Situation at 3/10, and Work-Life Balance at 4/10 steer the family toward a challenging outlook for quality of life – middle-income tier.",
      "alignmentValue": 4
    },
    {
      "key": "Quality of Life – Higher-Income Tier",
      "alignmentText": "Luxury services are thin; wealth management and elite schooling often require another city. Housing Situation at 3/10, Private Education at 5/10, and Family Life at 4/10 steer the family toward a challenging outlook for quality of life – higher-income tier.",
      "alignmentValue": 4
    },
    {
      "key": "Spacious Housing Benchmark (2k sq ft Rent)",
      "alignmentText": "Only a handful of listings surface each year; expect bidding wars and significant trade-offs. Housing Situation at 3/10 and Cost of Living (Optional) at 5/10 steer the family toward a challenging outlook for spacious housing benchmark (2k sq ft rent).",
      "alignmentValue": 4
    },
    {
      "key": "Community Living Opportunities",
      "alignmentText": "Community living is rare and often under-resourced, requiring significant personal effort to sustain. Community Vibes at 3/10, Meetups & Communities at 4/10, and Family Life at 4/10 steer the family toward a challenging outlook for community living opportunities.",
      "alignmentValue": 4
    },
    {
      "key": "Friendliness & Neighborliness Index",
      "alignmentText": "Neighbors keep to themselves and rarely volunteer help; we lean heavily on external networks. Community Vibes at 3/10, Meetups & Communities at 4/10, and Common Hobbies at 5/10 steer the family toward a challenging outlook for friendliness & neighborliness index.",
      "alignmentValue": 4
    },
    {
      "key": "Immigrant Sentiment – General",
      "alignmentText": "Harassment and exclusionary politics pose safety and stability risks. Welcoming of US Migrants at 1/10, Progressivism at 1/10, and Language & English Ubiquity at 3/10 steer the family toward an unsustainable outlook for immigrant sentiment – general.",
      "alignmentValue": 2
    },
    {
      "key": "Immigrant Sentiment – White Migrants",
      "alignmentText": "Hostility or exclusionary policies make us feel unwelcome despite best efforts. Welcoming of US Migrants at 1/10, Language & English Ubiquity at 3/10, and View of Them by Neighboring Countries at 2/10 steer the family toward an unsustainable outlook for immigrant sentiment – white migrants.",
      "alignmentValue": 2
    },
    {
      "key": "Surface Interaction Norms",
      "alignmentText": "Everyday interactions often feel curt or impatient, leaving little room for warmth. Community Vibes at 3/10, Nightlife Culture at 6/10, and Common Hobbies at 5/10 steer the family toward a challenging outlook for surface interaction norms.",
      "alignmentValue": 4
    },
    {
      "key": "Depth-Seeking Social Norms",
      "alignmentText": "Building close relationships is difficult; newcomers remain on the periphery for years. Community Vibes at 3/10, Meetups & Communities at 4/10, and What Is Intriguing at 6/10 steer the family toward a challenging outlook for depth-seeking social norms.",
      "alignmentValue": 4
    },
    {
      "key": "Personal Boundary & Bubble Norms",
      "alignmentText": "People ignore signals or treat boundary requests as unusual. Community Vibes at 3/10, Sex (Attitudes) at 2/10, and View of self at 4/10 steer the family toward a challenging outlook for personal boundary & bubble norms.",
      "alignmentValue": 3
    },
    {
      "key": "Moral, Honesty & Openness Expectations",
      "alignmentText": "Trust is low; we keep personal matters private to avoid gossip or judgment. Progressivism at 1/10, What Is Intriguing at 6/10, and Trust in Government at 3/10 steer the family toward a challenging outlook for moral, honesty & openness expectations.",
      "alignmentValue": 3
    },
    {
      "key": "Grooming & Beauty Investment",
      "alignmentText": "Looking impeccable is expected daily, creating stress for a low-maintenance family. Fashion Trends (Male) at 4/10 and Fashion Trends (Female) at 5/10 steer the family toward a challenging outlook for grooming & beauty investment.",
      "alignmentValue": 4
    },
    {
      "key": "Body Image & Fitness Pressure",
      "alignmentText": "Body shaming is common and influences opportunities or friendships. Fashion Trends (Male) at 4/10, Fashion Trends (Female) at 5/10, and Sex (Attitudes) at 2/10 steer the family toward a challenging outlook for body image & fitness pressure.",
      "alignmentValue": 4
    },
    {
      "key": "Fashion & Style Expectations",
      "alignmentText": "Designer or curated looks are assumed, pressuring constant wardrobe investment. Fashion Trends (Male) at 4/10 and Fashion Trends (Female) at 5/10 steer the family toward a challenging outlook for fashion & style expectations.",
      "alignmentValue": 4
    },
    {
      "key": "Flirting Boundaries & Consent Culture",
      "alignmentText": "Harassment complaints are common and rarely addressed seriously. Sex (Attitudes) at 2/10, LGBTQ+ Attitudes at 1/10, and Nightlife Culture at 6/10 steer the family toward a challenging outlook for flirting boundaries & consent culture.",
      "alignmentValue": 3
    },
    {
      "key": "Gendered Flirting Expectations",
      "alignmentText": "Communities enforce strict gendered behavior with little tolerance for experimentation. Gender Roles at 2/10, Gender Fluidity at 1/10, and Sex (Attitudes) at 2/10 steer the family toward an unsustainable outlook for gendered flirting expectations.",
      "alignmentValue": 2
    },
    {
      "key": "Monogamy vs. Non-Monogamy Acceptance",
      "alignmentText": "Hostile policies or social norms make non-monogamy extremely risky. Polyamory at 1/10, Sex (Attitudes) at 2/10, and Community Vibes at 3/10 steer the family toward an unsustainable outlook for monogamy vs. non-monogamy acceptance.",
      "alignmentValue": 2
    },
    {
      "key": "Promiscuity Attitudes",
      "alignmentText": "Public shaming or policy consequences follow disclosures about casual sex. Sex (Attitudes) at 2/10, Nightlife & Music at 6/10, and Community Vibes at 3/10 steer the family toward a challenging outlook for promiscuity attitudes.",
      "alignmentValue": 3
    },
    {
      "key": "Group & Multi-Partner Relationship Attitudes",
      "alignmentText": "Group relationships are untenable; social and legal consequences are severe. Polyamory at 1/10, Community Vibes at 3/10, and LGBTQ+ Attitudes at 1/10 steer the family toward an unsustainable outlook for group & multi-partner relationship attitudes.",
      "alignmentValue": 1
    },
    {
      "key": "Personal Space & Touch Norms",
      "alignmentText": "Physical proximity is unavoidable in many settings with limited accommodations. Community Vibes at 3/10, Sex (Attitudes) at 2/10, and Nightlife Culture at 6/10 steer the family toward a challenging outlook for personal space & touch norms.",
      "alignmentValue": 4
    },
    {
      "key": "Firearm Laws & Ownership Culture",
      "alignmentText": "Regulation is minimal and violence tied to firearms feels close to home. Safety & Crime at 3/10, State Ideology at 2/10, and Political System at 1/10 steer the family toward an unsustainable outlook for firearm laws & ownership culture.",
      "alignmentValue": 2
    },
    {
      "key": "Controlled Substance Policies",
      "alignmentText": "Even inadvertent infractions risk incarceration or deportation. Progressivism at 1/10, Political System at 1/10, and Safety & Crime at 3/10 steer the family toward an unsustainable outlook for controlled substance policies.",
      "alignmentValue": 2
    },
    {
      "key": "Drug Enforcement Climate",
      "alignmentText": "Enforcement climate is punitive and discriminatory, threatening our stability. Safety & Crime at 3/10, Progressivism at 1/10, and Authoritarian Backsliding Risk at 1/10 steer the family toward an unsustainable outlook for drug enforcement climate.",
      "alignmentValue": 2
    },
    {
      "key": "Mass Violence Incidence",
      "alignmentText": "We know victims or near-misses personally; anxiety is constant. Safety & Crime at 3/10 and Stability at 2/10 steer the family toward a challenging outlook for mass violence incidence.",
      "alignmentValue": 3
    },
    {
      "key": "Carceral Conditions & Prison Labor",
      "alignmentText": "Prisons operate as punitive work camps with minimal oversight. Authoritarian Backsliding Risk at 1/10, Safety & Crime at 3/10, and Perceived Corruption at 2/10 steer the family toward an unsustainable outlook for carceral conditions & prison labor.",
      "alignmentValue": 2
    },
    {
      "key": "Walkability & Pedestrian Safety",
      "alignmentText": "Walking is possible yet stressful due to gaps in sidewalks or aggressive driving. Public Transportation at 6/10, Housing Situation at 3/10, and Nature Access at 5/10 steer the family toward a mixed outlook for walkability & pedestrian safety.",
      "alignmentValue": 5
    },
    {
      "key": "Community Health Consciousness",
      "alignmentText": "Limited access to wellness programs or safe recreation spaces hinders goals. Healthcare (Citizens) at 3/10, Work-Life Balance at 4/10, and Community Vibes at 3/10 steer the family toward a challenging outlook for community health consciousness.",
      "alignmentValue": 3
    },
    {
      "key": "Processed Food Saturation",
      "alignmentText": "Healthy choices are overshadowed by processed fare in most neighborhoods. Cost of Living (Optional) at 5/10, Community Health Consciousness at 3/10, and Fresh & International Cuisine Access at 5/10 steer the family toward a challenging outlook for processed food saturation.",
      "alignmentValue": 4
    },
    {
      "key": "Fresh & International Cuisine Access",
      "alignmentText": "We rely on home cooking with imported ingredients to achieve desired variety. Nightlife & Music at 6/10, Common Hobbies at 5/10, and Meetups & Communities at 4/10 steer the family toward a mixed outlook for fresh & international cuisine access.",
      "alignmentValue": 5
    },
    {
      "key": "Depression Prevalence",
      "alignmentText": "Community struggles visibly with depression and lacks coordinated response. Seasonal Weather at 2/10, Work-Life Balance at 4/10, and Community Vibes at 3/10 steer the family toward a challenging outlook for depression prevalence.",
      "alignmentValue": 3
    },
    {
      "key": "Obesity Rate",
      "alignmentText": "Rates continue climbing; youth obesity impacts schools and recreation. Community Health Consciousness at 3/10, Work-Life Balance at 4/10, and Cost of Living (Optional) at 5/10 steer the family toward a challenging outlook for obesity rate.",
      "alignmentValue": 4
    },
    {
      "key": "Cancer Incidence",
      "alignmentText": "Multiple risk factors converge, making cancer a frequent community concern. Environment at 4/10, Healthcare (Citizens) at 3/10, and Community Health Consciousness at 3/10 steer the family toward a challenging outlook for cancer incidence.",
      "alignmentValue": 3
    },
    {
      "key": "Broader Job Market Resilience",
      "alignmentText": "Job market is volatile with frequent booms and busts across major employers. Economic Health at 3/10, Remote-Friendly Culture at 4/10, and Typical Software Salaries at 4/10 steer the family toward a challenging outlook for broader job market resilience.",
      "alignmentValue": 4
    }
  ]
}
